cli/__init__.py
cli/rpc.py
engine/__init__.py
engine/assets.py
engine/game.py
engine/input.py
engine/player.py
engine/window.py
red_panda_code-0.1.0.dist-info/licenses/LICENSE
runtime/__init__.py
runtime/errors.py
runtime/preprocessor.py
runtime/runner.py
runtime/sandbox.py
red_panda_code-0.1.0.dist-info/METADATA
red_panda_code-0.1.0.dist-info/WHEEL
red_panda_code-0.1.0.dist-info/top_level.txt
red_panda_code-0.1.0.dist-info/RECORD
