Metadata-Version: 2.4
Name: red-panda-code
Version: 0.1.0
Summary: A Python langauge for making 2D games.
Author-email: Lunar-Bytes <joar@strombackfamily.com>
License: MIT
Requires-Python: >=3.10
License-File: LICENSE
Dynamic: license-file
